naivefea/__init__.py
naivefea/helper.py
naivefea/analysis/__init__.py
naivefea/analysis/fea.py
naivefea/analysis/kernel.py
naivefea/analysis/processor.py
naivefea/analysis/solver.py
naivefea/constitutive/__init__.py
naivefea/constitutive/constitutive.py
naivefea/constitutive/tools.py
naivefea/constitutive/database/__init__.py
naivefea/constitutive/database/instantiate.py
naivefea/constitutive/database/steel.py
naivefea/element/__init__.py
naivefea/element/element.py
naivefea-0.1.2.1.dist-info/LICENSE
naivefea-0.1.2.1.dist-info/METADATA
naivefea-0.1.2.1.dist-info/WHEEL
naivefea-0.1.2.1.dist-info/top_level.txt
naivefea-0.1.2.1.dist-info/RECORD
