Metadata-Version: 2.1
Name: naivefea
Version: 0.1.2.1
Summary: A simple python library for 2D finite element analysis.
Home-page: https://github.com/MuTong320/NaiveFea
Author: Tong Mu
Author-email: mutong19970320@gmail.com
License: MIT
Platform: UNKNOWN
Classifier: License :: OSI Approved :: MIT License
Classifier: Programming Language :: Python
Classifier: Programming Language :: Python :: 3
Classifier: Programming Language :: Python :: 3.6
Classifier: Programming Language :: Python :: Implementation :: CPython
Classifier: Programming Language :: Python :: Implementation :: PyPy
Requires-Python: >=3.6.0
License-File: LICENSE
Requires-Dist: numpy
Requires-Dist: matplotlib
Requires-Dist: meshio
